docx2tiptap/__init__.py
docx2tiptap/comments_parser.py
docx2tiptap/constants.py
docx2tiptap/docx_exporter.py
docx2tiptap/docx_parser.py
docx2tiptap/models.py
docx2tiptap/numbering.py
docx2tiptap/revisions_parser.py
docx2tiptap/serializers.py
docx2tiptap/tiptap_converter.py
docx2tiptap/utils.py
docx2tiptap-0.2.1.dist-info/METADATA
docx2tiptap-0.2.1.dist-info/WHEEL
docx2tiptap-0.2.1.dist-info/licenses/LICENSE
docx2tiptap-0.2.1.dist-info/RECORD
