Metadata-Version: 2.4
Name: docx2tiptap
Version: 0.2.1
Summary: Parse DOCX files and convert to TipTap JSON format
Project-URL: Homepage, https://github.com/legalise-io/dedit/tree/main/docx2tiptap
Project-URL: Repository, https://github.com/legalise-io/dedit
Project-URL: Issues, https://github.com/legalise-io/dedit/issues
Author: Legalise.io
License-Expression: AGPL-3.0-or-later
License-File: LICENSE
Keywords: document,docx,parser,prosemirror,tiptap,word
Classifier: Development Status :: 3 - Alpha
Classifier: Intended Audience :: Developers
Classifier: License :: OSI Approved :: GNU Affero General Public License v3 or later (AGPLv3+)
Classifier: Programming Language :: Python :: 3
Classifier: Programming Language :: Python :: 3.10
Classifier: Programming Language :: Python :: 3.11
Classifier: Programming Language :: Python :: 3.12
Requires-Python: >=3.10
Requires-Dist: python-docx>=1.1.0
Provides-Extra: dev
Requires-Dist: build>=1.0.0; extra == 'dev'
Requires-Dist: pytest>=7.0.0; extra == 'dev'
Requires-Dist: twine>=5.0.0; extra == 'dev'
